Metadata-Version: 2.4
Name: pycrdt
Version: 0.12.44
Classifier: Development Status :: 4 - Beta
Classifier: Intended Audience :: Developers
Classifier: License :: OSI Approved :: MIT License
Classifier: Programming Language :: Python
Classifier: Programming Language :: Python :: 3.10
Classifier: Programming Language :: Python :: 3.11
Classifier: Programming Language :: Python :: 3.12
Classifier: Programming Language :: Python :: 3.13
Classifier: Programming Language :: Python :: 3.14
Classifier: Programming Language :: Rust
Classifier: Programming Language :: Python :: Implementation :: CPython
Classifier: Programming Language :: Python :: Implementation :: PyPy
Requires-Dist: anyio>=4.4.0,<5.0.0
Requires-Dist: typing-extensions>=4.14.0 ; python_full_version < '3.11'
License-File: LICENSE
Summary: Python bindings for Yrs
Keywords: crdt
Author-email: David Brochart <david.brochart@gmail.com>
Requires-Python: >=3.10
Project-URL: Homepage, https://github.com/y-crdt/pycrdt
